setup.py
BwETA/LLM_creator.py
BwETA/__init__.py
BwETA/layers.py
BwETA/model.py
BwETA.egg-info/PKG-INFO
BwETA.egg-info/SOURCES.txt
BwETA.egg-info/dependency_links.txt
BwETA.egg-info/requires.txt
BwETA.egg-info/top_level.txt