Metadata-Version: 2.1
Name: BwETA
Version: 0.14
Summary: A custom model testing module
Author: Boring._.wicked
Classifier: Programming Language :: Python :: 3
Classifier: License :: OSI Approved :: MIT License
